{
  "exhibitors": {
    "hall": "Exhibit Hall",
    "tsv_booth_count": 359,
    "geometry_booth_count": 366,
    "pdf_label_count": 366,
    "tsv_without_geometry": [],
    "geometry_without_tsv": [
      "1003",
      "1009",
      "1305",
      "1330",
      "1510",
      "16030",
      "1703"
    ],
    "geometry_without_tsv_total": 7,
    "match_rate": 100.0
  },
  "gaming": {
    "hall": "Gaming Hall C",
    "tsv_booth_count": 59,
    "geometry_booth_count": 63,
    "pdf_label_count": 62,
    "tsv_without_geometry": [
      "2328"
    ],
    "geometry_without_tsv": [
      "2200",
      "2338",
      "2426",
      "2509",
      "2526"
    ],
    "geometry_without_tsv_total": 5,
    "match_rate": 98.3
  }
}